{
	"Design": {
		"GB1A": {
			"id": "GB1A",
			"shape": "r",
			"width": 20,
			"height": 25,
			"image": ""
		},
		"GB1D": {
			"id": "GB1A",
			"shape": "r",
			"width": 20,
			"height": 25,
			"image": ""
		}
	},
	"Issue": {
		"GB21": {
			"issued": "1960-03-01",
			"design": "GB1A",
			"denom": "1d",
			"colors": "black",
			"subject": "",
			"image": "/file/stamp/GB1As.png"
		},
		"GB22":	{
			"issued": "1960-03-01",
			"design": "GB1D",
			"denom": "2d",
			"colors": "blue",
			"subject": "",
			"image": "/file/stamp/GB1Ds.png"
		},
		"GB23":	{
			"issued": "1960-03-01",
			"design": "GB1A",
			"denom": "3d",
			"colors": "red",
			"subject": "",
			"image": "/file/stamp/x.png"
		},
		"GB24":{
			"issued": "1960-03-01",
			"design": "GB1A",
			"denom": "1d",
			"colors": "black",
			"subject": "",
			"image": "/file/stamp/GB1As.png"
		},
		"GB25":{
			"issued": "1960-03-01",
			"design": "GB1D",
			"denom": "2d",
			"colors": "blue",
			"subject": "",
			"image": "/file/stamp/GB1Ds.png"
		},
		"GB26":{
			"issued": "1960-03-01",
			"design": "GB1A",
			"denom": "3d",
			"colors": "red",
			"subject": "",
			"image": "/file/stamp/x.png"
		},
		"GB27":{
			"issued": "1960-03-01",
			"design": "GB1A",
			"denom": "1d",
			"colors": "black",
			"subject": "",
			"image": "/file/stamp/GB1As.png"
		},
		"GB28":{
			"issued": "1960-03-01",
			"design": "GB1D",
			"denom": "2d",
			"colors": "blue",
			"subject": "",
			"image": "/file/stamp/GB1Ds.png"
		},
		"GB29":{
			"issued": "1960-03-01",
			"design": "GB1A",
			"denom": "3d",
			"colors": "red",
			"subject": "",
			"image": "/file/stamp/x.png"
		},
		"GB210":{
			"issued": "1960-03-01",
			"design": "GB1A",
			"denom": "3d",
			"colors": "red",
			"subject": "",
			"image": "/file/stamp/x.png"
		}
	}
}